Metadata-Version: 2.0
Name: elaphe3
Version: 0.1.1
Summary: Generates various barcodes using barcode.ps and pillow.
Home-page: https://github.com/graingert/elaphe
Author: Thomas Grainger
Author-email: elaphe3@graingert.co.uk
License: New BSD
Keywords: barcode convert postscript image graphics
Platform: UNKNOWN
Classifier: Development Status :: 4 - Beta
Classifier: Environment :: Console
Classifier: Intended Audience :: Developers
Classifier: License :: OSI Approved :: BSD License
Classifier: Operating System :: OS Independent
Classifier: Programming Language :: Python
Classifier: Topic :: Software Development :: Libraries :: Python Modules
Requires-Dist: pillow
